<?xml version="1.0" encoding="UTF-8"?>
<vivadoHLSLog:LogRoot xmlns:vivadoHLSLog="www.xilinx.com/vivadoHLSLog">
  <errorLogs>
    <logs>
      <synLog/>
      <simLog/>
      <mgLog/>
      <packageLog/>
      <csimLog/>
    </logs>
  </errorLogs>
  <warningLogs>
    <logs>
      <synLog>
        <logs message="@W [RTGEN-101] Port 'Timer/pps_en' has no fanin or fanout and is left dangling.&#xA;               Please use C simulation to confirm this function argument can be read from or written to." projectName="Timer" solutionName="solution1" date="2016-05-30T11:57:37.336+0500" type="Warning"/>
        <logs message="@W [RTGEN-101] Register 'trigger_count' is power-on initialization." projectName="Timer" solutionName="solution1" date="2016-05-30T11:57:37.315+0500" type="Warning"/>
        <logs message="@W [RTGEN-101] Register 'ticks' is power-on initialization." projectName="Timer" solutionName="solution1" date="2016-05-30T11:57:37.291+0500" type="Warning"/>
        <logs message="@W [RTGEN-101] Register 'state' is power-on initialization." projectName="Timer" solutionName="solution1" date="2016-05-30T11:57:37.278+0500" type="Warning"/>
        <logs message="@W [XFORM-311] Ignored reset directive (Timer.c:31:1): variable 'trigger_out' is not static or global variable." projectName="Timer" solutionName="solution1" date="2016-05-30T11:57:37.225+0500" type="Warning"/>
      </synLog>
      <simLog/>
      <mgLog/>
      <packageLog/>
      <csimLog/>
    </logs>
  </warningLogs>
</vivadoHLSLog:LogRoot>
